notes.txt
release.bash
setup.py
MetaPython.egg-info/PKG-INFO
MetaPython.egg-info/SOURCES.txt
MetaPython.egg-info/dependency_links.txt
MetaPython.egg-info/entry_points.txt
MetaPython.egg-info/paster_plugins.txt
MetaPython.egg-info/top_level.txt
MetaPython.egg-info/zip-safe
docs/Makefile
docs/conf.py
docs/index.rst
docs/make.bat
docs/presentations.rst
docs/roadmap.rst
docs/syntax_reference.rst
docs/examples/tutorial/namedtuple.mpy
docs/examples/tutorial/test.mpy
docs/examples/tutorial/test1.mpy
docs/examples/tutorial/test2.mpy
docs/images/Ouroboros.png
docs/images/already_got_one.jpg
docs/modules/core.rst
docs/modules/parse.rst
docs/presentations/intro.rst
docs/tools/rst2s5.py
docs/tools/rst_directive.py
examples/__init__.py
examples/dsl.mpy
examples/namedtuple.mpy
examples/use_dsl.mpy
metapython/__init__.py
metapython/core.py
metapython/parse.py
tests/all.py
tests/base.py
tests/cremove.mpy
tests/namedtuple.mpy
tests/test1.mpy
tests/test2.mpy
tests/test_cremove.mpy