Metadata-Version: 1.0
Name: MetaPython
Version: 0.2.2
Summary: Macro and code quoting facility for Python
Home-page: http://metapython.org
Author: Rick Copeland
Author-email: rick446@usa.net
License: MIT
Keywords: python,macro,code quoting,import hook
Platform: UNKNOWN
Classifier: Development Status :: 3 - Alpha
Classifier: Intended Audience :: Developers
Classifier: License :: OSI Approved :: MIT License
Classifier: Operating System :: OS Independent
Classifier: Programming Language :: Python
Classifier: Topic :: Software Development :: Code Generators
Classifier: Topic :: Software Development :: Interpreters
